rabbit_clarion/__init__.py
rabbit_clarion/calculate_wildlife_surface_densities.py
rabbit_clarion-1.0.0.dist-info/LICENSE
rabbit_clarion-1.0.0.dist-info/WHEEL
rabbit_clarion-1.0.0.dist-info/METADATA
rabbit_clarion-1.0.0.dist-info/RECORD
