Metadata-Version: 2.1
Name: rabbit_clarion
Version: 1.0.0
Summary: Module used in the repo conejos_clarion
Home-page: https://github.com/IslasGECI/rabbits_on_clarion_island
Author: Ciencia de Datos • GECI
Author-email: ciencia.datos@islas.org.mx
Requires-Python: >=3.9
Classifier: License :: OSI Approved :: GNU General Public License v3 or later (GPLv3+)
Requires-Dist: pandas
